aiogram_timepicker/__init__.py
aiogram_timepicker/result.py
aiogram_timepicker/utils.py
aiogram_timepicker/carousel/__init__.py
aiogram_timepicker/carousel/full/__init__.py
aiogram_timepicker/carousel/full/timepicker.py
aiogram_timepicker/carousel/full/utils.py
aiogram_timepicker/clock/__init__.py
aiogram_timepicker/clock/single/__init__.py
aiogram_timepicker/clock/single/base/__init__.py
aiogram_timepicker/clock/single/base/timepicker.py
aiogram_timepicker/clock/single/c24/__init__.py
aiogram_timepicker/clock/single/c24/timepicker.py
aiogram_timepicker/clock/single/c24/utils.py
aiogram_timepicker/clock/single/c24_ts3/__init__.py
aiogram_timepicker/clock/single/c24_ts3/timepicker.py
aiogram_timepicker/clock/single/c24_ts3/utils.py
aiogram_timepicker/clock/single/c60_ts3/__init__.py
aiogram_timepicker/clock/single/c60_ts3/timepicker.py
aiogram_timepicker/clock/single/c60_ts3/utils.py
aiogram_timepicker/clock/single/c60_ts5/__init__.py
aiogram_timepicker/clock/single/c60_ts5/timepicker.py
aiogram_timepicker/clock/single/c60_ts5/utils.py
aiogram_timepicker/panel/__init__.py
aiogram_timepicker/panel/full/__init__.py
aiogram_timepicker/panel/full/timepicker.py
aiogram_timepicker/panel/full/utils.py
aiogram_timepicker/panel/full/adapter/__init__.py
aiogram_timepicker/panel/full/adapter/minute.py
aiogram_timepicker/panel/full/adapter/second.py
aiogram_timepicker/panel/min_sec/__init__.py
aiogram_timepicker/panel/min_sec/timepicker.py
aiogram_timepicker/panel/min_sec/utils.py
aiogram_timepicker/panel/min_sec/adapter/__init__.py
aiogram_timepicker/panel/min_sec/adapter/minute.py
aiogram_timepicker/panel/min_sec/adapter/second.py
aiogram_timepicker/panel/single/__init__.py
aiogram_timepicker/panel/single/hour/__init__.py
aiogram_timepicker/panel/single/hour/timepicker.py
aiogram_timepicker/panel/single/hour/utils.py
aiogram_timepicker/panel/single/hour2/__init__.py
aiogram_timepicker/panel/single/hour2/timepicker.py
aiogram_timepicker/panel/single/hour2/utils.py
aiogram_timepicker-0.2.1.dist-info/LICENSE.txt
aiogram_timepicker-0.2.1.dist-info/METADATA
aiogram_timepicker-0.2.1.dist-info/WHEEL
aiogram_timepicker-0.2.1.dist-info/top_level.txt
aiogram_timepicker-0.2.1.dist-info/RECORD
