Metadata-Version: 2.1
Name: aiogram-timepicker
Version: 0.2.1
Summary: Time Selection tool for Aiogram Telegram Bots
Author-email: Marat Ashrafzianov <maratashdev@gmail.com>
Project-URL: Homepage, https://github.com/maratx86/aiogram-timepicker
Project-URL: Bug Tracker, https://github.com/maratx86/aiogram-timepicker/issues
Classifier: Programming Language :: Python :: 3
Classifier: License :: OSI Approved :: MIT License
Classifier: Operating System :: OS Independent
Requires-Python: >=3.7
License-File: LICENSE.txt
Requires-Dist: aiogram~=2.12
Requires-Dist: importlib-metadata; python_version < "3.7"
